SlyGmail/__init__.py
SlyGmail/__main__.py
SlyGmail/gmail.py
SlyGmail-0.2.0.dist-info/LICENSE
SlyGmail-0.2.0.dist-info/METADATA
SlyGmail-0.2.0.dist-info/WHEEL
SlyGmail-0.2.0.dist-info/top_level.txt
SlyGmail-0.2.0.dist-info/RECORD
