Metadata-Version: 2.1
Name: SlyGmail
Version: 0.2.0
Summary: No-boilerplate, async and typed Gmail access.
Author: Dunkyl 🔣🔣
License: MIT License
Project-URL: Homepage, https://docs.dunkyl.net/SlyGmail-Python/
Project-URL: Repository, https://github.com/dunkyl/SlyGmail-Python
Project-URL: Documentation, https://docs.dunkyl.net/SlyGmail-Python/
Project-URL: Bug Tracker, https://github.com/dunkyl/SlyGmail-Python/issues
Classifier: Operating System :: OS Independent
Requires-Python: >=3.10
License-File: LICENSE
Requires-Dist: SlyAPI (>=0.4.3)
Requires-Dist: aiofiles
Provides-Extra: dev
Requires-Dist: pytest ; extra == 'dev'
Requires-Dist: pytest-asyncio ; extra == 'dev'
